Workbook

Sheet RESUMEN_EJECUTIVO
B2: Métricas Globales de Estrategia:
B3: El portafolio general presenta una estructura de costos extraordinariamente sólida. Incluso con el mayor nivel de descuento, el promedio global supera la meta corporativa.
B5: Margen Promedio Lista Base | E5: =AVERAGE(ANÁLISIS_ESTRATÉGICO!L2:L801) -> 0.75799181
B6: Margen Promedio Lista 1 (20% DSCTO) | E6: =AVERAGE(ANÁLISIS_ESTRATÉGICO!M2:M801) -> 0.69748976
B7: Margen Promedio Lista 2 (30% DSCTO) | E7: =AVERAGE(ANÁLISIS_ESTRATÉGICO!N2:N801) -> 0.65427401
B8: Margen Promedio Lista 3 (40% DSCTO) | E8: =AVERAGE(ANÁLISIS_ESTRATÉGICO!O2:O801) -> 0.59665302
B11: Identificación e Impacto en los 9 artículos críticos:
B12: Se identificó un subgrupo de artículos cuyo costo de fábrica no soporta la estructura de descuentos, rompiendo la regla del 40% de margen.
B14: Código Unificador | C14: Frecuencia | D14: Margen Lista Base % | E14: Margen Lista 1 % | F14: Margen Lista 2 % | G14: Margen Lista 3 %
B15: =HYPERLINK("#'ANÁLISIS_ESTRATÉGICO'!C" & MATCH("RD_0025767", ANÁLISIS_ESTRATÉGICO!C:C, 0), "RD_0025767") -> RD_0025767 | C15: X | D15: 0.47900035 | E15: 0.34875044 | F15: 0.25571479 | G15: 0.13166726
B16: =HYPERLINK("#'ANÁLISIS_ESTRATÉGICO'!C" & MATCH("RD_0025771", ANÁLISIS_ESTRATÉGICO!C:C, 0), "RD_0025771") -> RD_0025771 | C16: X | D16: 0.53791021 | E16: 0.42238777 | F16: 0.33987173 | G16: 0.22985035
B17: =HYPERLINK("#'ANÁLISIS_ESTRATÉGICO'!C" & MATCH("RD_0026436", ANÁLISIS_ESTRATÉGICO!C:C, 0), "RD_0026436") -> RD_0026436 | C17: X | D17: 0.45274862 | E17: 0.31593578 | F17: 0.21821232 | G17: 0.087914368
B18: =HYPERLINK("#'ANÁLISIS_ESTRATÉGICO'!C" & MATCH("RD_0026439", ANÁLISIS_ESTRATÉGICO!C:C, 0), "RD_0026439") -> RD_0026439 | C18: X | D18: 0.50178187 | E18: 0.37722733 | F18: 0.28825981 | G18: 0.16963645
B19: =HYPERLINK("#'ANÁLISIS_ESTRATÉGICO'!C" & MATCH("RD_0026440", ANÁLISIS_ESTRATÉGICO!C:C, 0), "RD_0026440") -> RD_0026440 | C19: X | D19: 0.5156212 | E19: 0.3945265 | F19: 0.30803029 | G19: 0.192702
B20: =HYPERLINK("#'ANÁLISIS_ESTRATÉGICO'!C" & MATCH("RD_0025694", ANÁLISIS_ESTRATÉGICO!C:C, 0), "RD_0025694") -> RD_0025694 | C20: Y | D20: 0.58593574 | E20: 0.48241967 | F20: 0.40847963 | G20: 0.3098929
B21: =HYPERLINK("#'ANÁLISIS_ESTRATÉGICO'!C" & MATCH("RD_0025763", ANÁLISIS_ESTRATÉGICO!C:C, 0), "RD_0025763") -> RD_0025763 | C21: Y | D21: 0.57249725 | E21: 0.46562156 | F21: 0.38928179 | G21: 0.28749542
B22: =HYPERLINK("#'ANÁLISIS_ESTRATÉGICO'!C" & MATCH("RD_0026344", ANÁLISIS_ESTRATÉGICO!C:C, 0), "RD_0026344") -> RD_0026344 | C22: Y | D22: 0.61312857 | E22: 0.51641071 | F22: 0.44732653 | G22: 0.35521429
B23: =HYPERLINK("#'ANÁLISIS_ESTRATÉGICO'!C" & MATCH("RD_0026100", ANÁLISIS_ESTRATÉGICO!C:C, 0), "RD_0026100") -> RD_0026100 | C23: Z | D23: 0.61304975 | E23: 0.51631219 | F23: 0.44721393 | G23: 0.35508292
C24: Promedio | D24: =AVERAGE(D15:D23) -> 0.54129706 | E24: =AVERAGE(E15:E23) -> 0.42662133 | F24: =AVERAGE(F15:F23) -> 0.34471009 | G24: =AVERAGE(G15:G23) -> 0.23549511
B26: OBSERVACIONES RELEVANTES
B27: 1. Aplicar el descuento máximo (Lista 3) es seguro para la gran mayoría del portafolio (a excepción de los 9 productos). El catálogo general mantiene un margen promedio del 60%, superando cómodamente la meta del 40%.
B30: 2. La pérdida de rentabilidad está aislada exclusivamente en 9 códigos de repuestos, cuyo margen colapsa hasta un mínimo del 9% al aplicar la Lista 3.
B32: 3. El problema de estos 9 artículos críticos es que su costo de fábrica es desproporcionadamente alto frente a su precio de mercado. Arrancan con un margen base de apenas 54% (muy por debajo del 76% general), dejándolos un margen de maniobra reducido para soportar la cadena de descuentos.
B37: ESTRATEGIA (Plan de Acción)
B38: PROBLEMA | D38: ESTRATEGIA
B39: Los productos de alta rotación "X" entran en zona de alerta desde la lista 1 de descuentos. | D39: No podemos bloquear comercialmente los descuentos. Es urgente renegociar una reducción del precio de fábrica (25%-30%) apalancado por el alto volumen de ventas. Si el proveedor no cede se propone una estrategia de Venta Atada, en donde solo se autorizarán descuentos si el cliente incluye en su orden productos con un margen verde (>50%), asegurando que la factura tenga un margen mayor al 40%.
B48: Los productos de rotación media "Y" entran en riesgo en la lista 1 y 2 de descuentos. | D48: Bloquear en el sistema la Lista 3 para los tres artículos. Adicionalmente, para el código RD_0025763, el tope máximo permitido por sistema también puede ser la Lista 2, si es que consideramos que la reducción del PVP de la competencia es del 1% y no del 2%
B55: Producto de Baja Rotación "Z" rompe la meta en la lista 3 de descuentos. El costo de almacenamiento es un problema | D55: Limitar su venta a la Lista 2 garantiza el margen, pero no garantiza que se venda. Para incentivar su salida y liberar capital de trabajo, se proponen dos vías comerciales: 1. Autorizar el precio de la lista 3 pero solo si el cliente lo lleva en combo al comprar articulos de rotación "X" o si se usa como gancho para cerrar ventas por volumen; 2. Aceptar el 36% de margen en lista 3, asumiendo la meta como costo financiero de mantener el producto en la bodega.

Sheet ANÁLISIS_ESTRATÉGICO
A1: Frecuencia | B1: Código de artículo | C1: Código Unificador | D1: Marca | E1: Categoria Principal | F1: PrecioFábrica | G1: PVP Competencia | H1: Precio Lista CDR | I1: Lista 1 (20%) | J1: Lista 2 (30%) | K1: Lista 3 (40%) | L1: Margen Lista Base % | M1: Margen Lista 1 % | N1: Margen Lista 2 % | O1: Margen Lista 3 %
A2: X | B2: CDR-000010001 | C2: RD_0025689 | D2: CDR RODAMIENTOS | E2: RODAMIENTOS Y AFINES | F2: 5.5083333 | G2: =VLOOKUP(Tabla1[[#This Row],[Código Unificador]],PRECIOS_COMPETENCIA!B:D,3,FALSE) -> 23.2521 | H2: =Tabla1[[#This Row],[PVP Competencia]]*0.98 -> 22.787058 | I2: =Tabla1[[#This Row],[Precio Lista CDR]]*0.8 -> 18.229646 | J2: =Tabla1[[#This Row],[Precio Lista CDR]]*0.7 -> 15.950941 | K2: =Tabla1[[#This Row],[Precio Lista CDR]]*0.6 -> 13.672235 | L2: =(Tabla1[[#This Row],[Precio Lista CDR]]-Tabla1[[#This Row],[PrecioFábrica]])/Tabla1[[#This Row],[Precio Lista CDR]] -> 0.75826922 | M2: =(Tabla1[[#This Row],[Lista 1 (20%)]]-Tabla1[[#This Row],[PrecioFábrica]])/Tabla1[[#This Row],[Lista 1 (20%)]] -> 0.69783652 | N2: =(Tabla1[[#This Row],[Lista 2 (30%)]]-Tabla1[[#This Row],[PrecioFábrica]])/Tabla1[[#This Row],[Lista 2 (30%)]] -> 0.65467031 | O2: =(Tabla1[[#This Row],[Lista 3 (40%)]]-Tabla1[[#This Row],[PrecioFábrica]])/Tabla1[[#This Row],[Lista 3 (40%)]] -> 0.59711536
A3: X | B3: CDR-000010002 | C3: RD_0025690 | D3: CDR RODAMIENTOS | E3: RODAMIENTOS Y AFINES | F3: 4.35 | G3: =VLOOKUP(Tabla1[[#This Row],[Código Unificador]],PRECIOS_COMPETENCIA!B:D,3,FALSE) -> 16.99345 | H3: =Tabla1[[#This Row],[PVP Competencia]]*0.98 -> 16.653581 | I3: =Tabla1[[#This Row],[Precio Lista CDR]]*0.8 -> 13.322865 | J3: =Tabla1[[#This Row],[Precio Lista CDR]]*0.7 -> 11.657507 | K3: =Tabla1[[#This Row],[Precio Lista CDR]]*0.6 -> 9.9921486 | L3: =(Tabla1[[#This Row],[Precio Lista CDR]]-Tabla1[[#This Row],[PrecioFábrica]])/Tabla1[[#This Row],[Precio Lista CDR]] -> 0.73879492 | M3: =(Tabla1[[#This Row],[Lista 1 (20%)]]-Tabla1[[#This Row],[PrecioFábrica]])/Tabla1[[#This Row],[Lista 1 (20%)]] -> 0.67349365 | N3: =(Tabla1[[#This Row],[Lista 2 (30%)]]-Tabla1[[#This Row],[PrecioFábrica]])/Tabla1[[#This Row],[Lista 2 (30%)]] -> 0.62684988 | O3: =(Tabla1[[#This Row],[Lista 3 (40%)]]-Tabla1[[#This Row],[PrecioFábrica]])/Tabla1[[#This Row],[Lista 3 (40%)]] -> 0.5646582
A4: X | B4: CDR-000010003 | C4: RD_0025691 | D4: CDR RODAMIENTOS | E4: RODAMIENTOS Y AFINES | F4: 7.5666667 | G4: =VLOOKUP(Tabla1[[#This Row],[Código Unificador]],PRECIOS_COMPETENCIA!B:D,3,FALSE) -> 29.98 | H4: =Tabla1[[#This Row],[PVP Competencia]]*0.98 -> 29.3804 | I4: =Tabla1[[#This Row],[Precio Lista CDR]]*0.8 -> 23.50432 | J4: =Tabla1[[#This Row],[Precio Lista CDR]]*0.7 -> 20.56628 | K4: =Tabla1[[#This Row],[Precio Lista CDR]]*0.6 -> 17.62824 | L4: =(Tabla1[[#This Row],[Precio Lista CDR]]-Tabla1[[#This Row],[PrecioFábrica]])/Tabla1[[#This Row],[Precio Lista CDR]] -> 0.74245869 | M4: =(Tabla1[[#This Row],[Lista 1 (20%)]]-Tabla1[[#This Row],[PrecioFábrica]])/Tabla1[[#This Row],[Lista 1 (20%)]] -> 0.67807336 | N4: =(Tabla1[[#This Row],[Lista 2 (30%)]]-Tabla1[[#This Row],[PrecioFábrica]])/Tabla1[[#This Row],[Lista 2 (30%)]] -> 0.63208384 | O4: =(Tabla1[[#This Row],[Lista 3 (40%)]]-Tabla1[[#This Row],[PrecioFábrica]])/Tabla1[[#This Row],[Lista 3 (40%)]] -> 0.57076449
A5: Z | B5: CDR-000010004 | C5: RD_0025692 | D5: CDR RODAMIENTOS | E5: RODAMIENTOS Y AFINES | F5: 5.7833333 | G5: =VLOOKUP(Tabla1[[#This Row],[Código Unificador]],PRECIOS_COMPETENCIA!B:D,3,FALSE) -> 21.777967 | H5: =Tabla1[[#This Row],[PVP Competencia]]*0.98 -> 21.342407 | I5: =Tabla1[[#This Row],[Precio Lista CDR]]*0.8 -> 17.073926 | J5: =Tabla1[[#This Row],[Precio Lista CDR]]*0.7 -> 14.939685 | K5: =Tabla1[[#This Row],[Precio Lista CDR]]*0.6 -> 12.805444 | L5: =(Tabla1[[#This Row],[Precio Lista CDR]]-Tabla1[[#This Row],[PrecioFábrica]])/Tabla1[[#This Row],[Precio Lista CDR]] -> 0.72902151 | M5: =(Tabla1[[#This Row],[Lista 1 (20%)]]-Tabla1[[#This Row],[PrecioFábrica]])/Tabla1[[#This Row],[Lista 1 (20%)]] -> 0.66127689 | N5: =(Tabla1[[#This Row],[Lista 2 (30%)]]-Tabla1[[#This Row],[PrecioFábrica]])/Tabla1[[#This Row],[Lista 2 (30%)]] -> 0.61288787 | O5: =(Tabla1[[#This Row],[Lista 3 (40%)]]-Tabla1[[#This Row],[PrecioFábrica]])/Tabla1[[#This Row],[Lista 3 (40%)]] -> 0.54836918
A6: Z | B6: CDR-000010005 | C6: RD_0025693 | D6: CDR RODAMIENTOS | E6: RODAMIENTOS Y AFINES | F6: 13.541667 | G6: =VLOOKUP(Tabla1[[#This Row],[Código Unificador]],PRECIOS_COMPETENCIA!B:D,3,FALSE) -> 46.4125 | H6: =Tabla1[[#This Row],[PVP Competencia]]*0.98 -> 45.48425 | I6: =Tabla1[[#This Row],[Precio Lista CDR]]*0.8 -> 36.3874 | J6: =Tabla1[[#This Row],[Precio Lista CDR]]*0.7 -> 31.838975 | K6: =Tabla1[[#This Row],[Precio Lista CDR]]*0.6 -> 27.29055 | L6: =(Tabla1[[#This Row],[Precio Lista CDR]]-Tabla1[[#This Row],[PrecioFábrica]])/Tabla1[[#This Row],[Precio Lista CDR]] -> 0.70227789 | M6: =(Tabla1[[#This Row],[Lista 1 (20%)]]-Tabla1[[#This Row],[PrecioFábrica]])/Tabla1[[#This Row],[Lista 1 (20%)]] -> 0.62784737 | N6: =(Tabla1[[#This Row],[Lista 2 (30%)]]-Tabla1[[#This Row],[PrecioFábrica]])/Tabla1[[#This Row],[Lista 2 (30%)]] -> 0.57468271 | O6: =(Tabla1[[#This Row],[Lista 3 (40%)]]-Tabla1[[#This Row],[PrecioFábrica]])/Tabla1[[#This Row],[Lista 3 (40%)]] -> 0.50379649
A7: Y | B7: CDR-000010006 | C7: RD_0025694 | D7: CDR RODAMIENTOS | E7: RODAMIENTOS Y AFINES | F7: 20.816667 | G7: =VLOOKUP(Tabla1[[#This Row],[Código Unificador]],PRECIOS_COMPETENCIA!B:D,3,FALSE) -> 51.3 | H7: =Tabla1[[#This Row],[PVP Competencia]]*0.98 -> 50.274 | I7: =Tabla1[[#This Row],[Precio Lista CDR]]*0.8 -> 40.2192 | J7: =Tabla1[[#This Row],[Precio Lista CDR]]*0.7 -> 35.1918 | K7: =Tabla1[[#This Row],[Precio Lista CDR]]*0.6 -> 30.1644 | L7: =(Tabla1[[#This Row],[Precio Lista CDR]]-Tabla1[[#This Row],[PrecioFábrica]])/Tabla1[[#This Row],[Precio Lista CDR]] -> 0.58593574 | M7: =(Tabla1[[#This Row],[Lista 1 (20%)]]-Tabla1[[#This Row],[PrecioFábrica]])/Tabla1[[#This Row],[Lista 1 (20%)]] -> 0.48241967 | N7: =(Tabla1[[#This Row],[Lista 2 (30%)]]-Tabla1[[#This Row],[PrecioFábrica]])/Tabla1[[#This Row],[Lista 2 (30%)]] -> 0.40847963 | O7: =(Tabla1[[#This Row],[Lista 3 (40%)]]-Tabla1[[#This Row],[PrecioFábrica]])/Tabla1[[#This Row],[Lista 3 (40%)]] -> 0.3098929
A8: X | B8: CDR-000010007 | C8: RD_0025695 | D8: CDR RODAMIENTOS | E8: RODAMIENTOS Y AFINES | F8: 11.016667 | G8: =VLOOKUP(Tabla1[[#This Row],[Código Unificador]],PRECIOS_COMPETENCIA!B:D,3,FALSE) -> 43.226267 | H8: =Tabla1[[#This Row],[PVP Competencia]]*0.98 -> 42.361741 | I8: =Tabla1[[#This Row],[Precio Lista CDR]]*0.8 -> 33.889393 | J8: =Tabla1[[#This Row],[Precio Lista CDR]]*0.7 -> 29.653219 | K8: =Tabla1[[#This Row],[Precio Lista CDR]]*0.6 -> 25.417045 | L8: =(Tabla1[[#This Row],[Precio Lista CDR]]-Tabla1[[#This Row],[PrecioFábrica]])/Tabla1[[#This Row],[Precio Lista CDR]] -> 0.7399383 | M8: =(Tabla1[[#This Row],[Lista 1 (20%)]]-Tabla1[[#This Row],[PrecioFábrica]])/Tabla1[[#This Row],[Lista 1 (20%)]] -> 0.67492287 | N8: =(Tabla1[[#This Row],[Lista 2 (30%)]]-Tabla1[[#This Row],[PrecioFábrica]])/Tabla1[[#This Row],[Lista 2 (30%)]] -> 0.62848328 | O8: =(Tabla1[[#This Row],[Lista 3 (40%)]]-Tabla1[[#This Row],[PrecioFábrica]])/Tabla1[[#This Row],[Lista 3 (40%)]] -> 0.56656383
A9: X | B9: CDR-000010008 | C9: RD_0025696 | D9: CDR RODAMIENTOS | E9: RODAMIENTOS Y AFINES | F9: 11.433333 | G9: =VLOOKUP(Tabla1[[#This Row],[Código Unificador]],PRECIOS_COMPETENCIA!B:D,3,FALSE) -> 44.482933 | H9: =Tabla1[[#This Row],[PVP Competencia]]*0.98 -> 43.593275 | I9: =Tabla1[[#This Row],[Precio Lista CDR]]*0.8 -> 34.87462 | J9: =Tabla1[[#This Row],[Precio Lista CDR]]*0.7 -> 30.515292 | K9: =Tabla1[[#This Row],[Precio Lista CDR]]*0.6 -> 26.155965 | L9: =(Tabla1[[#This Row],[Precio Lista CDR]]-Tabla1[[#This Row],[PrecioFábrica]])/Tabla1[[#This Row],[Precio Lista CDR]] -> 0.73772713 | M9: =(Tabla1[[#This Row],[Lista 1 (20%)]]-Tabla1[[#This Row],[PrecioFábrica]])/Tabla1[[#This Row],[Lista 1 (20%)]] -> 0.67215891 | N9: =(Tabla1[[#This Row],[Lista 2 (30%)]]-Tabla1[[#This Row],[PrecioFábrica]])/Tabla1[[#This Row],[Lista 2 (30%)]] -> 0.62532447 | O9: =(Tabla1[[#This Row],[Lista 3 (40%)]]-Tabla1[[#This Row],[PrecioFábrica]])/Tabla1[[#This Row],[Lista 3 (40%)]] -> 0.56287855
A10: X | B10: CDR-000010009 | C10: RD_0025697 | D10: CDR RODAMIENTOS | E10: RODAMIENTOS Y AFINES | F10: 10.175 | G10: =VLOOKUP(Tabla1[[#This Row],[Código Unificador]],PRECIOS_COMPETENCIA!B:D,3,FALSE) -> 40.6878 | H10: =Tabla1[[#This Row],[PVP Competencia]]*0.98 -> 39.874044 | I10: =Tabla1[[#This Row],[Precio Lista CDR]]*0.8 -> 31.899235 | J10: =Tabla1[[#This Row],[Precio Lista CDR]]*0.7 -> 27.911831 | K10: =Tabla1[[#This Row],[Precio Lista CDR]]*0.6 -> 23.924426 | L10: =(Tabla1[[#This Row],[Precio Lista CDR]]-Tabla1[[#This Row],[PrecioFábrica]])/Tabla1[[#This Row],[Precio Lista CDR]] -> 0.74482147 | M10: =(Tabla1[[#This Row],[Lista 1 (20%)]]-Tabla1[[#This Row],[PrecioFábrica]])/Tabla1[[#This Row],[Lista 1 (20%)]] -> 0.68102684 | N10: =(Tabla1[[#This Row],[Lista 2 (30%)]]-Tabla1[[#This Row],[PrecioFábrica]])/Tabla1[[#This Row],[Lista 2 (30%)]] -> 0.63545924 | O10: =(Tabla1[[#This Row],[Lista 3 (40%)]]-Tabla1[[#This Row],[PrecioFábrica]])/Tabla1[[#This Row],[Lista 3 (40%)]] -> 0.57470245
A11: X | B11: CDR-000010010 | C11: RD_0025698 | D11: CDR RODAMIENTOS | E11: RODAMIENTOS Y AFINES | F11: 8.8666667 | G11: =VLOOKUP(Tabla1[[#This Row],[Código Unificador]],PRECIOS_COMPETENCIA!B:D,3,FALSE) -> 36.999 | H11: =Tabla1[[#This Row],[PVP Competencia]]*0.98 -> 36.25902 | I11: =Tabla1[[#This Row],[Precio Lista CDR]]*0.8 -> 29.007216 | J11: =Tabla1[[#This Row],[Precio Lista CDR]]*0.7 -> 25.381314 | K11: =Tabla1[[#This Row],[Precio Lista CDR]]*0.6 -> 21.755412 | L11: =(Tabla1[[#This Row],[Precio Lista CDR]]-Tabla1[[#This Row],[PrecioFábrica]])/Tabla1[[#This Row],[Precio Lista CDR]] -> 0.75546315 | M11: =(Tabla1[[#This Row],[Lista 1 (20%)]]-Tabla1[[#This Row],[PrecioFábrica]])/Tabla1[[#This Row],[Lista 1 (20%)]] -> 0.69432893 | N11: =(Tabla1[[#This Row],[Lista 2 (30%)]]-Tabla1[[#This Row],[PrecioFábrica]])/Tabla1[[#This Row],[Lista 2 (30%)]] -> 0.65066164 | O11: =(Tabla1[[#This Row],[Lista 3 (40%)]]-Tabla1[[#This Row],[PrecioFábrica]])/Tabla1[[#This Row],[Lista 3 (40%)]] -> 0.59243858
A12: X | B12: CDR-000010011 | C12: RD_0025699 | D12: CDR RODAMIENTOS | E12: RODAMIENTOS Y AFINES | F12: 8.05 | G12: =VLOOKUP(Tabla1[[#This Row],[Código Unificador]],PRECIOS_COMPETENCIA!B:D,3,FALSE) -> 35.2126 | H12: =Tabla1[[#This Row],[PVP Competencia]]*0.98 -> 34.508348 | I12: =Tabla1[[#This Row],[Precio Lista CDR]]*0.8 -> 27.606678 | J12: =Tabla1[[#This Row],[Precio Lista CDR]]*0.7 -> 24.155844 | K12: =Tabla1[[#This Row],[Precio Lista CDR]]*0.6 -> 20.705009 | L12: =(Tabla1[[#This Row],[Precio Lista CDR]]-Tabla1[[#This Row],[PrecioFábrica]])/Tabla1[[#This Row],[Precio Lista CDR]] -> 0.76672311 | M12: =(Tabla1[[#This Row],[Lista 1 (20%)]]-Tabla1[[#This Row],[PrecioFábrica]])/Tabla1[[#This Row],[Lista 1 (20%)]] -> 0.70840389 | N12: =(Tabla1[[#This Row],[Lista 2 (30%)]]-Tabla1[[#This Row],[PrecioFábrica]])/Tabla1[[#This Row],[Lista 2 (30%)]] -> 0.6667473 | O12: =(Tabla1[[#This Row],[Lista 3 (40%)]]-Tabla1[[#This Row],[PrecioFábrica]])/Tabla1[[#This Row],[Lista 3 (40%)]] -> 0.61120519
A13: Z | B13: CDR-000010012 | C13: RD_0025700 | D13: CDR RODAMIENTOS | E13: RODAMIENTOS Y AFINES | F13: 12.766667 | G13: =VLOOKUP(Tabla1[[#This Row],[Código Unificador]],PRECIOS_COMPETENCIA!B:D,3,FALSE) -> 48.8745 | H13: =Tabla1[[#This Row],[PVP Competencia]]*0.98 -> 47.89701 | I13: =Tabla1[[#This Row],[Precio Lista CDR]]*0.8 -> 38.317608 | J13: =Tabla1[[#This Row],[Precio Lista CDR]]*0.7 -> 33.527907 | K13: =Tabla1[[#This Row],[Precio Lista CDR]]*0.6 -> 28.738206 | L13: =(Tabla1[[#This Row],[Precio Lista CDR]]-Tabla1[[#This Row],[PrecioFábrica]])/Tabla1[[#This Row],[Precio Lista CDR]] -> 0.73345587 | M13: =(Tabla1[[#This Row],[Lista 1 (20%)]]-Tabla1[[#This Row],[PrecioFábrica]])/Tabla1[[#This Row],[Lista 1 (20%)]] -> 0.66681984 | N13: =(Tabla1[[#This Row],[Lista 2 (30%)]]-Tabla1[[#This Row],[PrecioFábrica]])/Tabla1[[#This Row],[Lista 2 (30%)]] -> 0.61922268 | O13: =(Tabla1[[#This Row],[Lista 3 (40%)]]-Tabla1[[#This Row],[PrecioFábrica]])/Tabla1[[#This Row],[Lista 3 (40%)]] -> 0.55575979
... A801: X | B801: CDR-000010800 | C801: RD_0026488 | D801: CDR RODAMIENTOS | E801: RODAMIENTOS Y AFINES | F801: 5.7416667 | G801: =VLOOKUP(Tabla1[[#This Row],[Código Unificador]],PRECIOS_COMPETENCIA!B:D,3,FALSE) -> 27.9829 | H801: =Tabla1[[#This Row],[PVP Competencia]]*0.98 -> 27.423242 | I801: =Tabla1[[#This Row],[Precio Lista CDR]]*0.8 -> 21.938594 | J801: =Tabla1[[#This Row],[Precio Lista CDR]]*0.7 -> 19.196269 | K801: =Tabla1[[#This Row],[Precio Lista CDR]]*0.6 -> 16.453945 | L801: =(Tabla1[[#This Row],[Precio Lista CDR]]-Tabla1[[#This Row],[PrecioFábrica]])/Tabla1[[#This Row],[Precio Lista CDR]] -> 0.79062772 | M801: =(Tabla1[[#This Row],[Lista 1 (20%)]]-Tabla1[[#This Row],[PrecioFábrica]])/Tabla1[[#This Row],[Lista 1 (20%)]] -> 0.73828465 | N801: =(Tabla1[[#This Row],[Lista 2 (30%)]]-Tabla1[[#This Row],[PrecioFábrica]])/Tabla1[[#This Row],[Lista 2 (30%)]] -> 0.70089674 | O801: =(Tabla1[[#This Row],[Lista 3 (40%)]]-Tabla1[[#This Row],[PrecioFábrica]])/Tabla1[[#This Row],[Lista 3 (40%)]] -> 0.6510462
K802: PROMEDIOS: | L802: =SUBTOTAL(101,Tabla1[Margen Lista Base %]) -> 0.75799181 | M802: =SUBTOTAL(101,Tabla1[Margen Lista 1 %]) -> 0.69748976 | N802: =SUBTOTAL(101,Tabla1[Margen Lista 2 %]) -> 0.65427401 | O802: =SUBTOTAL(101,Tabla1[Margen Lista 3 %]) -> 0.59665302

Sheet ANÁLISIS_ALTA_ROTACIÓN
A1: sin reducción
A2: Frecuencia | B2: Código de artículo | C2: Código Unificador | D2: Precio Fábrica | E2: PVP CDR | F2: Margen Lista Base % | G2: Margen Lista 1 % | H2: Margen Lista 2 % | I2: Margen Lista 3 %
A3: X | B3: CDR-000010079 | C3: RD_0025767 | D3: 51.558333 | E3: =100.98*0.98 -> 98.9604 | F3: 0.47900035 | G3: 0.34875044 | H3: 0.25571479 | I3: 0.13166726
A4: X | B4: CDR-000010083 | C4: RD_0025771 | D4: 56.791667 | E4: =125.41*0.98 -> 122.9018 | F4: 0.53791021 | G4: 0.42238777 | H4: 0.33987173 | I4: 0.22985035
A5: X | B5: CDR-000010748 | C5: RD_0026436 | D5: 73.166667 | E5: =136.427*0.98 -> 133.69846 | F5: 0.45274862 | G5: 0.31593578 | H5: 0.21821232 | I5: 0.087914368
A6: X | B6: CDR-000010751 | C6: RD_0026439 | D6: 80.25 | E6: =164.36125*0.98 -> 161.07403 | F6: 0.50178187 | G6: 0.37722733 | H6: 0.28825981 | I6: 0.16963645
A7: X | B7: CDR-000010752 | C7: RD_0026440 | D7: 80.291667 | E7: 169.14504 | F7: 0.5156212 | G7: 0.3945265 | H7: 0.30803029 | I7: 0.192702
A9: reducción del 25%
A10: Frecuencia | B10: Código de artículo | C10: Código Unificador | D10: Precio Fábrica | E10: PVP CDR | F10: Margen Lista Base % | G10: Margen Lista 1 % | H10: Margen Lista 2 % | I10: Margen Lista 3 %
A11: X | B11: CDR-000010079 | C11: RD_0025767 | D11: 38.67 | E11: =100.98*0.98 -> 98.9604 | F11: 0.61 | G11: 0.51 | H11: 0.44 | I11: 0.35
A12: X | B12: CDR-000010083 | C12: RD_0025771 | D12: 42.59 | E12: =125.41*0.98 -> 122.9018 | F12: 0.65 | G12: 0.57 | H12: 0.5 | I12: 0.42
A13: X | B13: CDR-000010748 | C13: RD_0026436 | D13: 54.88 | E13: =136.427*0.98 -> 133.69846 | F13: 0.59 | G13: 0.49 | H13: 0.41 | I13: 0.32
A14: X | B14: CDR-000010751 | C14: RD_0026439 | D14: 60.19 | E14: =164.36125*0.98 -> 161.07403 | F14: 0.63 | G14: 0.53 | H14: 0.47 | I14: 0.38
A15: X | B15: CDR-000010752 | C15: RD_0026440 | D15: 60.22 | E15: 169.14504 | F15: 0.64 | G15: 0.55 | H15: 0.48 | I15: 0.39
A17: reducción del 33,33%
A18: Frecuencia | B18: Código de artículo | C18: Código Unificador | D18: Precio Fábrica | E18: PVP CDR | F18: Margen Lista Base % | G18: Margen Lista 1 % | H18: Margen Lista 2 % | I18: Margen Lista 3 %
A19: X | B19: CDR-000010079 | C19: RD_0025767 | D19: 34.368785 | E19: =100.98*0.98 -> 98.9604 | F19: 0.65270164 | G19: 0.56587705 | H19: 0.50385948 | I19: 0.42116939
A20: X | B20: CDR-000010083 | C20: RD_0025771 | D20: 37.857325 | E20: =125.41*0.98 -> 122.9018 | F20: 0.69197095 | G20: 0.61496368 | H20: 0.5599585 | I20: 0.48661825
A21: X | B21: CDR-000010748 | C21: RD_0026436 | D21: 48.7729 | E21: =136.427*0.98 -> 133.69846 | F21: 0.63520223 | G21: 0.54400279 | H21: 0.47886033 | I21: 0.39200372
A22: X | B22: CDR-000010751 | C22: RD_0026439 | D22: 53.49465 | E22: =164.36125*0.98 -> 161.07403 | F22: 0.66788779 | G22: 0.58485974 | H22: 0.52555399 | I22: 0.44647965
A23: X | B23: CDR-000010752 | C23: RD_0026440 | D23: 53.522425 | E23: 169.14504 | F23: 0.67711309 | G23: 0.59639137 | H23: 0.53873299 | I23: 0.46185515

Sheet ANÁLISIS_MEDIA_ROTACIÓN
A1: Frecuencia | B1: Código de artículo | C1: Código Unificador | D1: Precio Fábrica | E1: PVP CDR | F1: Margen Lista Base % | G1: Margen Lista 1 % | H1: Margen Lista 2 % | I1: Margen Lista 3 %
A2: Y | B2: CDR-000010006 | C2: RD_0025694 | D2: 20.816667 | E2: 50.274 | F2: 0.58593574 | G2: 0.48241967 | H2: 0.40847963 | I2: 0.3098929
A3: Y | B3: CDR-000010075 | C3: RD_0025763 | D3: 45.816667 | E3: 107.1728 | F3: 0.57249725 | G3: 0.46562156 | H3: 0.38928179 | I3: 0.28749542
A4: Y | B4: CDR-000010656 | C4: RD_0026344 | D4: 78.025 | E4: 201.68199 | F4: 0.61312857 | G4: 0.51641071 | H4: 0.44732653 | I4: 0.35521429
A8: Frecuencia | B8: Código de artículo | C8: Código Unificador | D8: Precio Fábrica | E8: PVP CDR | F8: Margen Lista Base % | G8: Margen Lista 1 % | H8: Margen Lista 2 % | I8: Margen Lista 3 %
A9: Y | B9: CDR-000010006 | C9: RD_0025694 | D9: 20.816667 | E9: 50.274 | F9: 0.58593574 | G9: 0.48241967 | H9: 0.40847963 | I9: 0.3098929
A10: Y | B10: CDR-000010075 | C10: RD_0025763 | D10: 45.816667 | E10: 108.2664 | F10: 0.57681546 | G10: 0.47101933 | H10: 0.39545066 | I10: 0.29469243
A11: Y | B11: CDR-000010656 | C11: RD_0026344 | D11: 78.025 | E11: 201.68199 | F11: 0.61312857 | G11: 0.51641071 | H11: 0.44732653 | I11: 0.35521429
A15: Frecuencia | B15: Código de artículo | C15: Código Unificador | D15: Precio Fábrica | E15: PVP CDR | F15: Margen Lista Base % | G15: Margen Lista 1 % | H15: Margen Lista 2 % | I15: Margen Lista 3 %
A16: Y | B16: CDR-000010006 | C16: RD_0025694 | D16: 20.816667 | E16: 50.274 | F16: 0.58593574 | G16: 0.48241967 | H16: 0.40847963 | I16: 0.3098929
A17: Y | B17: CDR-000010075 | C17: RD_0025763 | D17: 45.816667 | E17: 107.1728 | F17: 0.57249725 | G17: 0.46562156 | H17: 0.4 | I17: 0.28749542
A18: Y | B18: CDR-000010656 | C18: RD_0026344 | D18: 78.025 | E18: 201.68199 | F18: 0.61312857 | G18: 0.51641071 | H18: 0.44732653 | I18: 0.35521429

Sheet PRECIOS_CDR
A1: Frecuencia | B1: Código de artículo | C1: Código Unificador | D1: Marca | E1: Categoria Principal | F1: PrecioFábrica
A2: X | B2: CDR-000010001 | C2: RD_0025689 | D2: CDR RODAMIENTOS | E2: RODAMIENTOS Y AFINES | F2: 5.5083333
A3: X | B3: CDR-000010002 | C3: RD_0025690 | D3: CDR RODAMIENTOS | E3: RODAMIENTOS Y AFINES | F3: 4.35
A4: X | B4: CDR-000010003 | C4: RD_0025691 | D4: CDR RODAMIENTOS | E4: RODAMIENTOS Y AFINES | F4: 7.5666667
A5: Z | B5: CDR-000010004 | C5: RD_0025692 | D5: CDR RODAMIENTOS | E5: RODAMIENTOS Y AFINES | F5: 5.7833333
A6: Z | B6: CDR-000010005 | C6: RD_0025693 | D6: CDR RODAMIENTOS | E6: RODAMIENTOS Y AFINES | F6: 13.541667
A7: Y | B7: CDR-000010006 | C7: RD_0025694 | D7: CDR RODAMIENTOS | E7: RODAMIENTOS Y AFINES | F7: 20.816667
A8: X | B8: CDR-000010007 | C8: RD_0025695 | D8: CDR RODAMIENTOS | E8: RODAMIENTOS Y AFINES | F8: 11.016667
A9: X | B9: CDR-000010008 | C9: RD_0025696 | D9: CDR RODAMIENTOS | E9: RODAMIENTOS Y AFINES | F9: 11.433333
A10: X | B10: CDR-000010009 | C10: RD_0025697 | D10: CDR RODAMIENTOS | E10: RODAMIENTOS Y AFINES | F10: 10.175
A11: X | B11: CDR-000010010 | C11: RD_0025698 | D11: CDR RODAMIENTOS | E11: RODAMIENTOS Y AFINES | F11: 8.8666667
A12: X | B12: CDR-000010011 | C12: RD_0025699 | D12: CDR RODAMIENTOS | E12: RODAMIENTOS Y AFINES | F12: 8.05
A13: Z | B13: CDR-000010012 | C13: RD_0025700 | D13: CDR RODAMIENTOS | E13: RODAMIENTOS Y AFINES | F13: 12.766667
... A801: X | B801: CDR-000010800 | C801: RD_0026488 | D801: CDR RODAMIENTOS | E801: RODAMIENTOS Y AFINES | F801: 5.7416667

Sheet PRECIOS_COMPETENCIA
A1: Código de artículo | B1: Código Unificador | C1: Marca | D1: PVP Competencia
A2: HIV_0010258 | B2: RD_0025854 | C2: HIV RODAMIENTOS | D2: 18.351033
A3: HIV_0010259 | B3: RD_0025855 | C3: HIV RODAMIENTOS | D3: 17.1369
A4: HIV_0010260 | B4: RD_0025856 | C4: HIV RODAMIENTOS | D4: 17.56755
A5: HIV_0010261 | B5: RD_0025857 | C5: HIV RODAMIENTOS | D5: 16.98175
A6: HIV_0010262 | B6: RD_0025858 | C6: HIV RODAMIENTOS | D6: 17.1514
A7: HIV_0010263 | B7: RD_0025859 | C7: HIV RODAMIENTOS | D7: 19.600933
A8: HIV_0010264 | B8: RD_0025860 | C8: HIV RODAMIENTOS | D8: 18.351033
A9: HIV_0010265 | B9: RD_0025861 | C9: HIV RODAMIENTOS | D9: 17.3863
A10: HIV_0010266 | B10: RD_0025862 | C10: HIV RODAMIENTOS | D10: 18.84355
A11: HIV_0010267 | B11: RD_0025863 | C11: HIV RODAMIENTOS | D11: 21.410533
A12: HIV_0010268 | B12: RD_0025864 | C12: HIV RODAMIENTOS | D12: 21.425275
A13: HIV_0010269 | B13: RD_0025865 | C13: HIV RODAMIENTOS | D13: 17.741067
... A801: HIV_987795 | B801: RD_0025853 | C801: HIV RODAMIENTOS | D801: 17.044583
